asgi_lifespan_middleware/__init__.py
asgi_lifespan_middleware/_middleware.py
asgi_lifespan_middleware/_types.py
asgi_lifespan_middleware/py.typed
asgi_lifespan_middleware-0.1.3.dist-info/LICENSE.txt
asgi_lifespan_middleware-0.1.3.dist-info/WHEEL
asgi_lifespan_middleware-0.1.3.dist-info/METADATA
asgi_lifespan_middleware-0.1.3.dist-info/RECORD
